odoo/addons/product_brand_tag/README.rst
odoo/addons/product_brand_tag/__init__.py
odoo/addons/product_brand_tag/__manifest__.py
odoo/addons/product_brand_tag/i18n/product_brand_tag.pot
odoo/addons/product_brand_tag/models/__init__.py
odoo/addons/product_brand_tag/models/product_brand.py
odoo/addons/product_brand_tag/models/product_brand_tag.py
odoo/addons/product_brand_tag/models/product_brand_tag_mixin.py
odoo/addons/product_brand_tag/readme/CONTRIBUTORS.rst
odoo/addons/product_brand_tag/readme/DESCRIPTION.rst
odoo/addons/product_brand_tag/security/ir.model.access.csv
odoo/addons/product_brand_tag/security/ir_rule.xml
odoo/addons/product_brand_tag/static/description/icon.png
odoo/addons/product_brand_tag/static/description/index.html
odoo/addons/product_brand_tag/tests/__init__.py
odoo/addons/product_brand_tag/tests/test_product_brand.py
odoo/addons/product_brand_tag/views/product_brand_tag_view.xml
odoo/addons/product_brand_tag/views/product_brand_view.xml
odoo14_addon_product_brand_tag-14.0.1.1.1.dist-info/METADATA
odoo14_addon_product_brand_tag-14.0.1.1.1.dist-info/WHEEL
odoo14_addon_product_brand_tag-14.0.1.1.1.dist-info/top_level.txt
odoo14_addon_product_brand_tag-14.0.1.1.1.dist-info/RECORD
