Metadata-Version: 2.1
Name: odoo14-addon-product-brand-tag
Version: 14.0.1.1.1
Summary: Add tags to product brand
Home-page: https://github.com/OCA/brand
Author: Camptocamp, Odoo Community Association (OCA)
Author-email: support@odoo-community.org
License: AGPL-3
Platform: UNKNOWN
Classifier: Programming Language :: Python
Classifier: Framework :: Odoo
Classifier: License :: OSI Approved :: GNU Affero General Public License v3
Requires-Python: >=3.6
Requires-Dist: odoo14-addon-product-brand
Requires-Dist: odoo (<14.1dev,>=14.0a)
